cartagen/__init__.py
cartagen/_version.py
cartagen/algorithms/__init__.py
cartagen/algorithms/blocks/building_elimination.py
cartagen/algorithms/buildings/__init__.py
cartagen/algorithms/buildings/amalgamation.py
cartagen/algorithms/buildings/displacement.py
cartagen/algorithms/buildings/regularization.py
cartagen/algorithms/buildings/simplification.py
cartagen/algorithms/buildings/squaring.py
cartagen/algorithms/lines/__init__.py
cartagen/algorithms/lines/bends.py
cartagen/algorithms/lines/breaks.py
cartagen/algorithms/lines/coalescence.py
cartagen/algorithms/network/__init__.py
cartagen/algorithms/network/branching_crossroads.py
cartagen/algorithms/network/dead_ends.py
cartagen/algorithms/network/dual_carriageways.py
cartagen/algorithms/network/roundabouts.py
cartagen/algorithms/points/__init__.py
cartagen/algorithms/points/covering.py
cartagen/algorithms/points/heatmap.py
cartagen/algorithms/points/kmeans.py
cartagen/algorithms/points/labelgrid.py
cartagen/algorithms/points/quadtree.py
cartagen/data/__init__.py
cartagen/enrichment/__init__.py
cartagen/enrichment/network/__init__.py
cartagen/enrichment/network/branching_crossroads.py
cartagen/enrichment/network/dead_ends.py
cartagen/enrichment/network/dual_carriageways.py
cartagen/enrichment/network/roundabouts.py
cartagen/enrichment/network/rural_areas.py
cartagen/enrichment/network/strokes.py
cartagen/enrichment/urban/__init__.py
cartagen/enrichment/urban/block_measures.py
cartagen/enrichment/urban/building_measures.py
cartagen/enrichment/urban/urban_areas.py
cartagen/evaluation/__init__.py
cartagen/evaluation/constraint_satisfaction.py
cartagen/evaluation/constraint_monitors/__init__.py
cartagen/evaluation/constraint_monitors/building_size_monitor.py
cartagen/evaluation/constraint_monitors/constraint_monitor.py
cartagen/evaluation/constraint_monitors/object_granularity_monitor.py
cartagen/evaluation/constraint_monitors/object_position_monitor.py
cartagen/evaluation/constraint_monitors/test_monitors.py
cartagen-1.0.2.dist-info/LICENSE.md
cartagen-1.0.2.dist-info/METADATA
cartagen-1.0.2.dist-info/WHEEL
cartagen-1.0.2.dist-info/top_level.txt
cartagen-1.0.2.dist-info/RECORD
