Metadata-Version: 2.1
Name: cartagen
Version: 1.0.2
Summary: Cartographic generalisation of spatial objects
Author: Guillaume Touya, Justin Berli, Azelle Courtial
Maintainer: CartAGen contributors
License: EUPL-1.2
Project-URL: Documentation, https://cartagen.readthedocs.io/
Project-URL: Repository, https://github.com/LostInZoom/cartagen
Keywords: gis,cartography,generalisation
Classifier: Development Status :: 4 - Beta
Classifier: Intended Audience :: Science/Research
Classifier: Operating System :: Unix
Classifier: Operating System :: MacOS
Classifier: Operating System :: Microsoft :: Windows
Classifier: Programming Language :: Python :: 3.10
Classifier: Programming Language :: Python :: 3.11
Classifier: Topic :: Scientific/Engineering :: GIS
Requires-Python: >=3.10
License-File: LICENSE.md
Requires-Dist: numpy
Requires-Dist: shapely
Requires-Dist: geopandas
Requires-Dist: matplotlib
Requires-Dist: networkx
